csvtorasa/__init__.py
csvtorasa/main.py
csvtorasa/data/nlu_sample_format_for_conversion.csv
csvtorasa-0.1.1.dist-info/LICENSE
csvtorasa-0.1.1.dist-info/METADATA
csvtorasa-0.1.1.dist-info/WHEEL
csvtorasa-0.1.1.dist-info/top_level.txt
csvtorasa-0.1.1.dist-info/RECORD
